jodo/__init__.py
jodo/db.py
jodo/main.py
jodo-0.3.3.dist-info/entry_points.txt
jodo-0.3.3.dist-info/licenses/LICENSE
jodo-0.3.3.dist-info/WHEEL
jodo-0.3.3.dist-info/METADATA
jodo-0.3.3.dist-info/RECORD
