Metadata-Version: 2.4
Name: jodo
Version: 0.3.3
Summary: One CLI to rule them all
Author-email: James Falcon <therealfalcon@gmail.com>
Requires-Python: >=3.10
Classifier: License :: OSI Approved :: Apache Software License
License-File: LICENSE
Requires-Dist: pycloudlib~=1!10.10
Requires-Dist: pytest ; extra == "test"
Requires-Dist: ruff ; extra == "test"
Project-URL: Home, https://github.com/TheRealFalcon/jodo
Provides-Extra: test
